plasma/__init__.py
plasma/debug.py
plasma/enum.py
plasma/layout.py
plasma/node.py
qtile_plasma-1.5.6.dist-info/LICENSE
qtile_plasma-1.5.6.dist-info/METADATA
qtile_plasma-1.5.6.dist-info/WHEEL
qtile_plasma-1.5.6.dist-info/top_level.txt
qtile_plasma-1.5.6.dist-info/RECORD
