Metadata-Version: 2.1
Name: qtile-plasma
Version: 1.5.6
Summary: A flexible, tree-based layout for Qtile
Home-page: https://github.com/numirias/qtile-plasma
Author: numirias
Author-email: numirias@users.noreply.github.com
License: MIT
Platform: UNKNOWN
Classifier: Development Status :: 4 - Beta
Classifier: License :: OSI Approved :: MIT License
Classifier: Operating System :: Unix
Classifier: Programming Language :: Python
Classifier: Programming Language :: Python :: 3
Classifier: Programming Language :: Python :: 3.7
Classifier: Programming Language :: Python :: 3.8
Classifier: Programming Language :: Python :: 3.9
Classifier: Topic :: Desktop Environment :: Window Managers
Requires-Python: >=3
Requires-Dist: xcffib (>=0.5.0)
Requires-Dist: qtile (>=0.17)
